ViNexPy/__init__.py
ViNexPy/_main.py
ViNexPy/cli.py
ViNexPy/static/index.html
ViNexPy/tests/__init__.py
ViNexPy/tests/conftest.py
ViNexPy/tests/test_utils.py
vinexpy-0.2.1.dist-info/entry_points.txt
vinexpy-0.2.1.dist-info/LICENSE.md
vinexpy-0.2.1.dist-info/METADATA
vinexpy-0.2.1.dist-info/WHEEL
vinexpy-0.2.1.dist-info/RECORD
