Metadata-Version: 2.1
Name: ViNexPy
Version: 0.2.1
Summary: Python script to stream data from vicon nexus to unity
Home-page: https://pypi.org/project/ViNexPy
License: MIT
Author: Omang
Author-email: omangbaheti@gmail.com
Requires-Python: >=3.8,<4.0
Classifier: Development Status :: 1 - Planning
Classifier: License :: OSI Approved :: MIT License
Classifier: Natural Language :: English
Classifier: Operating System :: OS Independent
Classifier: Programming Language :: Python
Classifier: Programming Language :: Python :: 3
Classifier: Programming Language :: Python :: 3.8
Classifier: Programming Language :: Python :: 3.9
Classifier: Programming Language :: Python :: 3.10
Classifier: Programming Language :: Python :: 3.11
Classifier: Programming Language :: Python :: 3.12
Requires-Dist: Flask-RESTful (>=0.3.9,<0.4.0)
Requires-Dist: alive-progress (>=2.4.1,<3.0.0)
Requires-Dist: click (>=8.1.3,<9.0.0)
Requires-Dist: flask_restful (>=0.3.8,<0.4.0)
Requires-Dist: loguru (>=0.5.0,<0.6.0)
Requires-Dist: msgpack (>=1.0.4,<2.0.0)
Requires-Dist: pandas (>=1.5.1,<2.0.0)
Project-URL: Documentation, https://vicon_nexus_unity_stream_py.readthedocs.io
Project-URL: Repository, https://github.com/omangbaheti/vicon-nexus-unity-stream-py
